brom.py
brom-1.0.1b9.dist-info/LICENSE.txt
brom-1.0.1b9.dist-info/METADATA
brom-1.0.1b9.dist-info/WHEEL
brom-1.0.1b9.dist-info/top_level.txt
brom-1.0.1b9.dist-info/RECORD
