Metadata-Version: 2.1
Name: brom
Version: 1.0.1b9
Summary: Модуль, обеспечивающий взаимодействие с расширением «Бром» для 1С:Предприятие.
Home-page: https://brom.itworks.group
Author: Anton Shaganov (ITworks Ltd.)
Author-email: info@itworks.group
License: UNKNOWN
Project-URL: Documentation, https://brom.itworks.group/documentation/
Platform: UNKNOWN
Classifier: Programming Language :: Python :: 3
Classifier: License :: OSI Approved :: MIT License
Classifier: Operating System :: OS Independent
Requires-Python: >=3.6
Requires-Dist: zeep
